swarmauri/__init__.py
swarmauri/cli.py
swarmauri/importer.py
swarmauri/interface_registry.py
swarmauri/plugin_citizenship_registry.py
swarmauri/plugin_manager.py
swarmauri-0.7.5.dist-info/LICENSE
swarmauri-0.7.5.dist-info/METADATA
swarmauri-0.7.5.dist-info/WHEEL
swarmauri-0.7.5.dist-info/RECORD
