Metadata-Version: 2.3
Name: swarmauri
Version: 0.7.5
Summary: Namespace package for components, packages, and plugins within the Swarmauri framework.
License: Apache-2.0
Author: Jacob Stewart
Author-email: jacob@swarmauri.com
Requires-Python: >=3.10,<3.13
Classifier: License :: OSI Approved :: Apache Software License
Classifier: Programming Language :: Python :: 3.10
Classifier: Programming Language :: Python :: 3.11
Classifier: Programming Language :: Python :: 3.12
Provides-Extra: default
Provides-Extra: full
Requires-Dist: httpx (>=0.27.0)
Requires-Dist: pydantic (>=2.9.2)
Requires-Dist: swarmauri_base
Requires-Dist: swarmauri_core
Requires-Dist: swarmauri_distance_minkowski ; extra == "default"
Requires-Dist: swarmauri_distance_minkowski ; extra == "full"
Requires-Dist: swarmauri_embedding_doc2vec ; extra == "default"
Requires-Dist: swarmauri_embedding_doc2vec ; extra == "full"
Requires-Dist: swarmauri_embedding_nmf ; extra == "default"
Requires-Dist: swarmauri_embedding_nmf ; extra == "full"
Requires-Dist: swarmauri_parser_beautifulsoupelement ; extra == "default"
Requires-Dist: swarmauri_parser_beautifulsoupelement ; extra == "full"
Requires-Dist: swarmauri_parser_keywordextractor ; extra == "default"
Requires-Dist: swarmauri_parser_keywordextractor ; extra == "full"
Requires-Dist: swarmauri_standard
Requires-Dist: swarmauri_tool_matplotlib ; extra == "default"
Requires-Dist: swarmauri_tool_matplotlib ; extra == "full"
Requires-Dist: swarmauri_vectorstore_doc2vec ; extra == "default"
Requires-Dist: swarmauri_vectorstore_doc2vec ; extra == "full"
Requires-Dist: toml (>=0.10.2)
Requires-Dist: typing_extensions
